kirara_ai/__init__.py
kirara_ai/__main__.py
kirara_ai/entry.py
kirara_ai/internal.py
kirara_ai/logger.py
kirara_ai/alembic/README
kirara_ai/alembic/env.py
kirara_ai/alembic/script.py.mako
kirara_ai/alembic/__pycache__/env.cpython-312.pyc
kirara_ai/alembic/versions/4a364dbb8dab_initial_migration.py
kirara_ai/alembic/versions/__pycache__/4a364dbb8dab_initial_migration.cpython-312.pyc
kirara_ai/config/config_loader.py
kirara_ai/config/global_config.py
kirara_ai/database/__init__.py
kirara_ai/database/manager.py
kirara_ai/events/__init__.py
kirara_ai/events/application.py
kirara_ai/events/event_bus.py
kirara_ai/events/im.py
kirara_ai/events/listen.py
kirara_ai/events/llm.py
kirara_ai/events/plugin.py
kirara_ai/events/workflow.py
kirara_ai/events/tracing/__init__.py
kirara_ai/events/tracing/base.py
kirara_ai/events/tracing/llm.py
kirara_ai/im/__init__.py
kirara_ai/im/adapter.py
kirara_ai/im/im_registry.py
kirara_ai/im/manager.py
kirara_ai/im/message.py
kirara_ai/im/profile.py
kirara_ai/im/sender.py
kirara_ai/ioc/__init__.py
kirara_ai/ioc/container.py
kirara_ai/ioc/inject.py
kirara_ai/llm/adapter.py
kirara_ai/llm/llm_manager.py
kirara_ai/llm/llm_registry.py
kirara_ai/llm/format/__init__.py
kirara_ai/llm/format/message.py
kirara_ai/llm/format/request.py
kirara_ai/llm/format/response.py
kirara_ai/mcp/__init__.py
kirara_ai/mcp/manager.py
kirara_ai/mcp/models.py
kirara_ai/media/__init__.py
kirara_ai/media/manager.py
kirara_ai/media/media_object.py
kirara_ai/media/metadata.py
kirara_ai/media/carrier/__init__.py
kirara_ai/media/carrier/provider.py
kirara_ai/media/carrier/registry.py
kirara_ai/media/carrier/service.py
kirara_ai/media/types/__init__.py
kirara_ai/media/types/media_type.py
kirara_ai/media/utils/__init__.py
kirara_ai/media/utils/mime.py
kirara_ai/memory/entry.py
kirara_ai/memory/memory_manager.py
kirara_ai/memory/registry.py
kirara_ai/memory/composes/__init__.py
kirara_ai/memory/composes/base.py
kirara_ai/memory/composes/builtin_composes.py
kirara_ai-3.2.0.dist-info/licenses/LICENSE
kirara_ai-3.2.0.dist-info/METADATA
kirara_ai-3.2.0.dist-info/WHEEL
kirara_ai-3.2.0.dist-info/entry_points.txt
kirara_ai-3.2.0.dist-info/top_level.txt
kirara_ai-3.2.0.dist-info/RECORD
