Metadata-Version: 2.4
Name: kirara-ai
Version: 3.2.0
Summary: A framework for building AI agents
Author-email: Lss233 <i@lss233.com>
License-Expression: AGPL-3.0-only
Project-URL: Homepage, https://github.com/lss233/chatgpt-mirai-qq-bot
Project-URL: Bug Tracker, https://github.com/lss233/chatgpt-mirai-qq-bot/issues
Project-URL: Documentation, https://kirara-docs.app.lss233.com
Classifier: Programming Language :: Python :: 3
Classifier: Operating System :: OS Independent
Requires-Python: >=3.9
License-File: LICENSE
Requires-Dist: pydantic>=2.0.0
Requires-Dist: pydantic-core>=2.27.2
Requires-Dist: ruamel.yaml
Requires-Dist: pytest
Requires-Dist: pytest-asyncio
Requires-Dist: python-telegram-bot
Requires-Dist: telegramify-markdown
Requires-Dist: loguru
Requires-Dist: aiohttp
Requires-Dist: requests
Requires-Dist: quart>=0.18.4
Requires-Dist: quart-cors>=0.7.0
Requires-Dist: fastapi>=0.110.0
Requires-Dist: wechatpy
Requires-Dist: pycryptodome
Requires-Dist: redis[hiredis]
Requires-Dist: bcrypt>=4.0.1
Requires-Dist: PyJWT>=2.8.0
Requires-Dist: hypercorn>=0.15.0
Requires-Dist: psutil>=5.9.0
Requires-Dist: setuptools
Requires-Dist: tomli>=2.0.0
Requires-Dist: pre-commit
Requires-Dist: curl_cffi
Requires-Dist: python-magic; platform_system != "Windows"
Requires-Dist: python-magic-bin; platform_system == "Windows"
Requires-Dist: ymbotpy
Requires-Dist: Pillow
Requires-Dist: pytz
Requires-Dist: sqlalchemy
Requires-Dist: alembic
Dynamic: license-file
